vec2pg/__init__.py
vec2pg/cli.py
vec2pg/plugins/__init__.py
vec2pg/plugins/pinecone.py
vec2pg-2024.6.0.dist-info/LICENSE
vec2pg-2024.6.0.dist-info/METADATA
vec2pg-2024.6.0.dist-info/WHEEL
vec2pg-2024.6.0.dist-info/entry_points.txt
vec2pg-2024.6.0.dist-info/RECORD
